{
  "swagger": "2.0",
  "info": {
    "title": "Node Setup",
    "description": "API documentation",
    "version": "1.0.0"
  },
  "host": "localhost:3000",
  "basePath": "/api/v1",
  "schemes": "http",
  "paths": {
    "/user/sign-up": {
      "post": {
        "tags": [
          "User"
        ],
        "description": "User signup",
        "parameters": [
          {
            "name": "body",
            "in": "body",
            "schema": {
              "type": "object",
              "properties": {
                "password": {
                  "example": "any"
                },
                "email": {
                  "example": "any"
                }
              }
            }
          }
        ],
        "responses": {
          "default": {
            "description": ""
          }
        }
      }
    },
    "/user/sign-in": {
      "post": {
        "description": "",
        "parameters": [
          {
            "name": "body",
            "in": "body",
            "schema": {
              "type": "object",
              "properties": {
                "email": {
                  "example": "any"
                },
                "password": {
                  "example": "any"
                }
              }
            }
          }
        ],
        "responses": {
          "default": {
            "description": ""
          }
        }
      }
    },
    "/user/add-organization": {
      "post": {
        "description": "",
        "parameters": [
          {
            "name": "authorization",
            "in": "header",
            "type": "string"
          },
          {
            "name": "body",
            "in": "body",
            "schema": {
              "type": "object",
              "properties": {
                "organization_name": {
                  "example": "any"
                }
              }
            }
          }
        ],
        "responses": {
          "default": {
            "description": ""
          }
        }
      }
    },
    "/user/get-my-organizations": {
      "get": {
        "description": "",
        "parameters": [
          {
            "name": "authorization",
            "in": "header",
            "type": "string"
          }
        ],
        "responses": {
          "default": {
            "description": ""
          }
        }
      }
    },
    "/user/update-organization": {
      "put": {
        "description": "",
        "parameters": [
          {
            "name": "authorization",
            "in": "header",
            "type": "string"
          },
          {
            "name": "body",
            "in": "body",
            "schema": {
              "type": "object",
              "properties": {
                "organization_id": {
                  "example": "any"
                },
                "organization_name": {
                  "example": "any"
                }
              }
            }
          }
        ],
        "responses": {
          "default": {
            "description": ""
          }
        }
      }
    },
    "/user/delete-organization/{organization_id}": {
      "delete": {
        "description": "",
        "parameters": [
          {
            "name": "organization_id",
            "in": "path",
            "required": true,
            "type": "string"
          },
          {
            "name": "authorization",
            "in": "header",
            "type": "string"
          }
        ],
        "responses": {
          "default": {
            "description": ""
          }
        }
      }
    },
    "/user/add-member": {
      "post": {
        "description": "",
        "parameters": [
          {
            "name": "authorization",
            "in": "header",
            "type": "string"
          },
          {
            "name": "body",
            "in": "body",
            "schema": {
              "type": "object",
              "properties": {
                "organization_id": {
                  "example": "any"
                },
                "member_email": {
                  "example": "any"
                },
                "member_phone": {
                  "example": "any"
                }
              }
            }
          }
        ],
        "responses": {
          "default": {
            "description": ""
          }
        }
      }
    },
    "/user/get-member-list/{organization_id}": {
      "get": {
        "description": "",
        "parameters": [
          {
            "name": "organization_id",
            "in": "path",
            "required": true,
            "type": "string"
          },
          {
            "name": "authorization",
            "in": "header",
            "type": "string"
          },
          {
            "name": "search",
            "in": "query",
            "type": "string"
          },
          {
            "name": "limit",
            "in": "query",
            "type": "string"
          },
          {
            "name": "offset",
            "in": "query",
            "type": "string"
          }
        ],
        "responses": {
          "default": {
            "description": ""
          }
        }
      }
    },
    "/user/update-member": {
      "put": {
        "description": "",
        "parameters": [
          {
            "name": "authorization",
            "in": "header",
            "type": "string"
          },
          {
            "name": "body",
            "in": "body",
            "schema": {
              "type": "object",
              "properties": {
                "organization_id": {
                  "example": "any"
                },
                "member_id": {
                  "example": "any"
                },
                "member_email": {
                  "example": "any"
                },
                "member_phone": {
                  "example": "any"
                }
              }
            }
          }
        ],
        "responses": {
          "default": {
            "description": ""
          }
        }
      }
    },
    "/user/delete-member/{member_id}": {
      "delete": {
        "description": "",
        "parameters": [
          {
            "name": "member_id",
            "in": "path",
            "required": true,
            "type": "string"
          },
          {
            "name": "authorization",
            "in": "header",
            "type": "string"
          }
        ],
        "responses": {
          "default": {
            "description": ""
          }
        }
      }
    },
    "/admin/login": {
      "post": {
        "description": "",
        "parameters": [
          {
            "name": "body",
            "in": "body",
            "schema": {
              "type": "object",
              "properties": {
                "email": {
                  "example": "any"
                },
                "password": {
                  "example": "any"
                }
              }
            }
          }
        ],
        "responses": {
          "default": {
            "description": ""
          }
        }
      }
    },
    "/admin/subscription-plan/": {
      "get": {
        "description": "",
        "responses": {
          "default": {
            "description": ""
          }
        }
      },
      "post": {
        "description": "",
        "responses": {
          "default": {
            "description": ""
          }
        }
      }
    },
    "/admin/subscription-plan/{id}": {
      "put": {
        "description": "",
        "parameters": [
          {
            "name": "id",
            "in": "path",
            "required": true,
            "type": "string"
          }
        ],
        "responses": {
          "default": {
            "description": ""
          }
        }
      },
      "delete": {
        "description": "",
        "parameters": [
          {
            "name": "id",
            "in": "path",
            "required": true,
            "type": "string"
          }
        ],
        "responses": {
          "default": {
            "description": ""
          }
        }
      }
    }
  }
}